tdsense/__init__.py
tdsense/clustering.py
tdsense/plot.py
tdsense/utils.py
tdsense-0.1.3.11.dist-info/METADATA
tdsense-0.1.3.11.dist-info/WHEEL
tdsense-0.1.3.11.dist-info/top_level.txt
tdsense-0.1.3.11.dist-info/RECORD
