Metadata-Version: 2.1
Name: tdsense
Version: 0.1.3.11
Summary: A package to simplify the analytics on time series with Teradata Vantage.
Author: Denis Molin
Requires-Python: >=3.6
Requires-Dist: teradataml (>=17.10)
Requires-Dist: pandas
Requires-Dist: numpy
Requires-Dist: scipy (>1.7.0)
Requires-Dist: scikit-learn
Requires-Dist: matplotlib (>3.0.0)
Requires-Dist: tqdm
Requires-Dist: imageio
